soldet/SolitonDetector.py
soldet/__init__.py
soldet/classifier.py
soldet/data_download.py
soldet/dataset.py
soldet/mhat_metric.py
soldet/object_detector.py
soldet/pipeline.py
soldet/tf_helper.py
soldet-1.0.0.dist-info/licenses/LICENSE.txt
soldet-1.0.0.dist-info/METADATA
soldet-1.0.0.dist-info/WHEEL
soldet-1.0.0.dist-info/top_level.txt
soldet-1.0.0.dist-info/RECORD
