Metadata-Version: 2.4
Name: soldet
Version: 1.0.0
Summary: A package for solitonic feature detection in absorption images of Bose-Einstein condensates, with wider use for cold atom image analysis.
Author: Shangjie Guo, Sophia M. Koh, Amilson R. Fritsch, Ian B. Spielman, Justyna P. Zwolak
Maintainer-email: Michael Doris <mjdoris@umd.edu>, "Justyna P. Zwolak" <jpzwolak@umd.edu>
License-Expression: NIST-Software
Project-URL: Homepage, https://github.com/usnistgov/SolDet/
Classifier: Intended Audience :: Science/Research
Classifier: Programming Language :: Python :: 3
Classifier: Topic :: Scientific/Engineering
Classifier: Operating System :: Microsoft :: Windows
Classifier: Operating System :: Unix
Classifier: Operating System :: MacOS
Requires-Python: >=3.7
License-File: LICENSE.txt
Requires-Dist: numpy>=1.22.0
Requires-Dist: scikit-learn>=0.23.1
Requires-Dist: scipy>=1.6.3
Requires-Dist: tensorflow>=2.7.2
Requires-Dist: tqdm>=4.47.0
Requires-Dist: matplotlib>=3.2.2
Requires-Dist: lmfit>=1.0.1
Requires-Dist: h5py>=3.1.0
Requires-Dist: requests>=2.31.0
Requires-Dist: pandas>=1.0.5
Requires-Dist: seaborn>=0.10.1
Dynamic: license-file
